lostruct/__init__.py
lostruct/lostruct.py
tests/__init__.py
tests/test_bench.py
tests/test_fns.py
lostruct-0.0.4.dist-info/LICENSE
lostruct-0.0.4.dist-info/METADATA
lostruct-0.0.4.dist-info/WHEEL
lostruct-0.0.4.dist-info/top_level.txt
lostruct-0.0.4.dist-info/RECORD
