Metadata-Version: 2.1
Name: lostruct
Version: 0.0.4
Summary: Re-implementation of lostruct in Python, used to compare local population structure across populations.
Home-page: https://github.com/jguhlin/lostruct-py
Author: Joseph Guhlin
Author-email: joseph.guhlin@gmail.com
License: UNKNOWN
Project-URL: Bug Reports, https://github.com/jguhlin/lostruct-py/issues
Project-URL: Source, https://github.com/jguhlin/lostruct-py
Project-URL: R-lang version, https://github.com/petrelharp/local_pca
Project-URL: Original Method Paper, https://www.genetics.org/content/211/1/289
Keywords: structure,population,genomics,bioinformatics,PCA,MDS
Platform: UNKNOWN
Classifier: Programming Language :: Python :: 3
Classifier: License :: OSI Approved :: Python Software Foundation License
Classifier: Operating System :: OS Independent
Classifier: Intended Audience :: Science/Research
Classifier: Topic :: Scientific/Engineering :: Bio-Informatics
Classifier: Development Status :: 4 - Beta
Requires-Python: >=3.6
Requires-Dist: numpy
Requires-Dist: numba
Requires-Dist: cyvcf2
Requires-Dist: sparse
